{
    "name": "git-annex",
    "aliases": [],
    "versions": [
        {
            "name": "8.20210622",
            "sha256": "a1cef631ef2cc0c977580eacaa1294d7617727df99214920ca6e8f3172bae03e",
            "url": "https://downloads.kitenet.net/.git/annex/objects/KM/Ff/SHA256E-s51276461--a1cef631ef2cc0c977580eacaa1294d7617727df99214920ca6e8f3172bae03e.tar.gz/SHA256E-s51276461--a1cef631ef2cc0c977580eacaa1294d7617727df99214920ca6e8f3172bae03e.tar.gz"
        }
    ],
    "build_system": "Package",
    "conflicts": [
        {
            "name": "platform=darwin",
            "spec": "",
            "description": "Darwin is not supported."
        },
        {
            "name": "platform=windows",
            "spec": "",
            "description": "Windows is not supported."
        }
    ],
    "variants": [
        {
            "name": "standalone",
            "default": false,
            "description": "Install git-annex fully standalone incl. git"
        }
    ],
    "homepage": "https://git-annex.branchable.com",
    "maintainers": [],
    "patches": [],
    "resources": [],
    "description": " git-annex allows managing files with git, without checking the file\ncontents into git. While that may seem paradoxical, it is useful when\ndealing with files larger than git can currently easily handle, whether\ndue to limitations in memory, time, or disk space.\n",
    "dependencies": [
        {
            "name": "git",
            "description": "Git is a free and open source distributed version control system\ndesigned to handle everything from small to very large projects with\nspeed and efficiency."
        }
    ],
    "dependent_to": []
}