{
    "name": "go",
    "aliases": [
        {
            "name": "golang",
            "alias_for": "go"
        }
    ],
    "versions": [
        {
            "name": "1.22.4",
            "sha256": "fed720678e728a7ca30ba8d1ded1caafe27d16028fab0232b8ba8e22008fb784"
        },
        {
            "name": "1.22.2",
            "sha256": "374ea82b289ec738e968267cac59c7d5ff180f9492250254784b2044e90df5a9"
        },
        {
            "name": "1.22.1",
            "sha256": "79c9b91d7f109515a25fc3ecdaad125d67e6bdb54f6d4d98580f46799caea321"
        },
        {
            "name": "1.22.0",
            "sha256": "4d196c3d41a0d6c1dfc64d04e3cc1f608b0c436bd87b7060ce3e23234e1f4d5c"
        },
        {
            "name": "1.21.6",
            "sha256": "124926a62e45f78daabbaedb9c011d97633186a33c238ffc1e25320c02046248"
        },
        {
            "name": "1.21.5",
            "sha256": "285cbbdf4b6e6e62ed58f370f3f6d8c30825d6e56c5853c66d3c23bcdb09db19"
        }
    ],
    "latest_version": "1.22.4",
    "build_system": "Package",
    "conflicts": [],
    "variants": [
        {
            "name": "build_system",
            "default": "generic",
            "description": "Build systems supported by the package"
        }
    ],
    "homepage": "https://go.dev",
    "maintainers": [
        "alecbcs"
    ],
    "patches": [],
    "resources": [],
    "description": "The golang compiler and build environment\n",
    "dependencies": [
        {
            "name": "bash",
            "description": "The GNU Project's Bourne Again SHell."
        },
        {
            "name": "git",
            "description": "Git is a free and open source distributed version control system\ndesigned to handle everything from small to very large projects with\nspeed and efficiency."
        },
        {
            "name": "go-or-gccgo-bootstrap",
            "description": "The GNU Compiler Collection includes front ends for C, C++, Objective-C,\nFortran, Ada, and Go, as well as libraries for these languages."
        }
    ],
    "dependent_to": []
}