{
    "name": "mathematica",
    "aliases": [],
    "versions": [
        {
            "name": "12.1.1",
            "sha256": "ad47b886be4a9864d70f523f792615a051d4ebc987d9a0f654b645b4eb43b30a",
            "expand": false
        },
        {
            "name": "12.0.0",
            "sha256": "b9fb71e1afcc1d72c200196ffa434512d208fa2920e207878433f504e58ae9d7",
            "expand": false
        }
    ],
    "build_system": "Package",
    "conflicts": [],
    "variants": [],
    "homepage": "https://www.wolfram.com/mathematica/",
    "maintainers": [],
    "patches": [],
    "resources": [],
    "description": "Mathematica: high-powered computation with thousands of Wolfram Language\nfunctions, natural language input, real-world data, mobile support.\nNote: A manual download is required for Mathematica. Spack will search\nyour current directory for the download file. Alternatively, add this\nfile to a mirror so that Spack can find it. For instructions on how to\nset up a mirror, see http://spack.readthedocs.io/en/latest/mirrors.html\n",
    "dependencies": [],
    "dependent_to": []
}