{
    "aliases": [],
    "build_system": "MakefilePackage",
    "conflicts": [
        {
            "description": null,
            "name": "arch=windows-None-None",
            "spec": "build_system=makefile"
        }
    ],
    "dependencies": [
        {
            "description": "COLLIER: A Complex One-Loop LIbrary with Extended Regularizations for\nthe numerical evaluation of one-loop scalar and tensor integrals\nappearing in perturbative relativistic quantum field theory.",
            "name": "collier"
        },
        {
            "description": "GNU Make is a tool which controls the generation of executables and\nother non-source files of a program from the program's source files.",
            "name": "gmake"
        }
    ],
    "dependent_to": [],
    "description": "Prophecy4f is a Monte Carlo integrator for Higgs decays H -> WW/ZZ -> 4\nfermions.\n",
    "homepage": "https://prophecy4f.hepforge.org/",
    "latest_version": "3.0.2",
    "maintainers": [
        "haralmha",
        "vvolkl"
    ],
    "name": "prophecy4f",
    "patches": [],
    "resources": [],
    "variants": [
        {
            "default": "makefile",
            "description": "Build systems supported by the package",
            "name": "build_system"
        }
    ],
    "versions": [
        {
            "name": "3.0.2",
            "sha256": "01e6ad4d7e913082c1dcabd589173f5d962086dd7860c710f14a0528d8d80eb7"
        }
    ]
}