{
    "name": "psm",
    "aliases": [],
    "versions": [
        {
            "name": "3.3",
            "sha256": "034b10e24d9f2967ef0f8d0f828572295e89cdfa1ba30c35e288b9b23c3dab8f",
            "preferred": true
        },
        {
            "name": "2017-04-28",
            "commit": "604758e"
        }
    ],
    "build_system": "MakefilePackage",
    "conflicts": [
        {
            "name": "platform=windows",
            "spec": "",
            "description": "None"
        },
        {
            "name": "%gcc@6:",
            "spec": "@3.3",
            "description": "None"
        }
    ],
    "variants": [],
    "homepage": "https://github.com/intel/psm",
    "maintainers": [],
    "patches": [],
    "resources": [],
    "description": "Intel Performance scaled messaging library\n",
    "dependencies": [
        {
            "name": "uuid",
            "description": "Util-linux is a suite of essential utilities for any Linux system."
        }
    ],
    "dependent_to": [
        {
            "name": "mvapich2",
            "description": "Mvapich2 is a High-Performance MPI Library for clusters with diverse\nnetworks (InfiniBand, Omni-Path, Ethernet/iWARP, and RoCE) and computing\nplatforms (x86 (Intel and AMD), ARM and OpenPOWER)"
        },
        {
            "name": "libfabric",
            "description": "The Open Fabrics Interfaces (OFI) is a framework focused on exporting\nfabric communication services to applications."
        }
    ]
}