{
    "name": "py-cryptography",
    "aliases": [],
    "versions": [
        {
            "name": "35.0.0",
            "sha256": "9933f28f70d0517686bd7de36166dda42094eac49415459d9bdf5e7df3e0086d"
        },
        {
            "name": "3.4.8",
            "sha256": "94cc5ed4ceaefcbe5bf38c8fba6a21fc1d365bb8fb826ea1688e3370b2e24a1c"
        },
        {
            "name": "3.4.7",
            "sha256": "3d10de8116d25649631977cb37da6cbdd2d6fa0e0281d014a5b7d337255ca713"
        },
        {
            "name": "2.7",
            "sha256": "e6347742ac8f35ded4a46ff835c60e68c22a536a8ae5c4422966d06946b6d4c6"
        },
        {
            "name": "2.3.1",
            "sha256": "8d10113ca826a4c29d5b85b2c4e045ffa8bad74fb525ee0eceb1d38d4c70dfd6"
        },
        {
            "name": "1.8.1",
            "sha256": "323524312bb467565ebca7e50c8ae5e9674e544951d28a2904a50012a8828190"
        }
    ],
    "build_system": "PythonPackage",
    "conflicts": [],
    "variants": [
        {
            "name": "idna",
            "default": false,
            "description": "Deprecated U-label support"
        }
    ],
    "homepage": "https://github.com/pyca/cryptography",
    "maintainers": [
        "adamjstewart"
    ],
    "patches": [],
    "resources": [],
    "description": "cryptography is a package which provides cryptographic recipes and\nprimitives to Python developers\n",
    "dependencies": [
        {
            "name": "python",
            "description": "The Python programming language."
        },
        {
            "name": "py-pip",
            "description": "The PyPA recommended tool for installing Python packages."
        },
        {
            "name": "py-wheel",
            "description": "A built-package format for Python."
        },
        {
            "name": "py-setuptools",
            "description": "A Python utility that aids in the process of downloading, building,\nupgrading, installing, and uninstalling Python packages."
        },
        {
            "name": "py-setuptools-rust",
            "description": "Setuptools rust extension plugin."
        },
        {
            "name": "py-cffi",
            "description": "Foreign Function Interface for Python calling C code"
        },
        {
            "name": "py-asn1crypto",
            "description": "Python ASN.1 library with a focus on performance and a pythonic API"
        },
        {
            "name": "py-six",
            "description": "Python 2 and 3 compatibility utilities."
        },
        {
            "name": "py-idna",
            "description": "Internationalized Domain Names for Python (IDNA 2008 and UTS #46)"
        },
        {
            "name": "py-enum34",
            "description": "Python 3.4 Enum backported to 3.3, 3.2, 3.1, 2.7, 2.6, 2.5, and 2.4."
        },
        {
            "name": "py-ipaddress",
            "description": "Python 3.3's ipaddress for older Python versions"
        },
        {
            "name": "openssl",
            "description": "OpenSSL is an open source project that provides a robust, commercial-\ngrade, and full-featured toolkit for the Transport Layer Security (TLS)\nand Secure Sockets Layer (SSL) protocols. It is also a general-purpose\ncryptography library."
        }
    ],
    "dependent_to": [
        {
            "name": "py-azure-cli",
            "description": "Microsoft Azure Command-Line Tools."
        },
        {
            "name": "py-requests-ntlm",
            "description": "This package allows for HTTP NTLM authentication using the requests\nlibrary."
        },
        {
            "name": "py-azure-keyvault-keys",
            "description": "Microsoft Azure Key Vault Keys Client Library for Python."
        },
        {
            "name": "py-oauthlib",
            "description": "A generic, spec-compliant, thorough implementation of the OAuth\nrequest-signing logic"
        },
        {
            "name": "py-pymysql",
            "description": "Pure-Python MySQL client library"
        },
        {
            "name": "py-urllib3",
            "description": "HTTP library with thread-safe connection pooling, file post, and more."
        },
        {
            "name": "py-azure-keyvault",
            "description": "Microsoft Azure Key Vault Client Libraries for Python."
        },
        {
            "name": "py-adal",
            "description": "The ADAL for Python library makes it easy for python application to\nauthenticate to Azure Active Directory (AAD) in order to access AAD\nprotected web resources. DEPRECATED: replaced by MSAL Python."
        },
        {
            "name": "py-secretstorage",
            "description": "Python bindings to FreeDesktop.org Secret Service API."
        },
        {
            "name": "py-azure-storage-blob",
            "description": "Microsoft Azure Blob Storage Client Library for Python"
        },
        {
            "name": "py-globus-sdk",
            "description": "Globus SDK for Python"
        },
        {
            "name": "py-merlin",
            "description": "Merlin Workflow for HPC."
        },
        {
            "name": "py-azure-multiapi-storage",
            "description": "Microsoft Azure Storage Client Library for Python with multi API version\nsupport."
        },
        {
            "name": "py-pyjwt",
            "description": "JSON Web Token implementation in Python"
        },
        {
            "name": "py-azure-identity",
            "description": "Microsoft Azure Identity Library for Python."
        },
        {
            "name": "py-azure-storage-common",
            "description": "Microsoft Azure Storage Common Client Library for Python."
        },
        {
            "name": "py-ansible",
            "description": "Ansible is a radically simple IT automation platform that makes your\napplications and systems easier to deploy."
        },
        {
            "name": "py-azureml-core",
            "description": "The azureml-core contains functionality for creating and managing: *\nAzure Machine Learning workspaces, experiments and runs; * Machine\nlearning compute respources; * Models, images and web services."
        },
        {
            "name": "py-paramiko",
            "description": "SSH2 protocol library"
        },
        {
            "name": "py-pyopenssl",
            "description": "High-level wrapper around a subset of the OpenSSL library. Note: The\nPython Cryptographic Authority strongly suggests the use of\npyca/cryptography where possible. If you are using pyOpenSSL for\nanything other than making a TLS connection you should move to\ncryptography and drop your pyOpenSSL dependency."
        }
    ]
}