{
    "name": "py-pykokkos-base",
    "aliases": [],
    "versions": [
        {
            "name": "main",
            "branch": "main",
            "submodules": false
        },
        {
            "name": "0.0.5",
            "commit": "45f6e892c007ab124fabb3a545f4744537eafb55",
            "submodules": false
        },
        {
            "name": "0.0.4",
            "commit": "2efe1220d0128d3f2d371c9ed5234c4978d73a77",
            "submodules": false
        },
        {
            "name": "0.0.3",
            "commit": "4fe4421ac624ba2efe1eee265153e690622a18a5",
            "submodules": false
        }
    ],
    "latest_version": "0.0.5",
    "build_system": "CMakePackage",
    "conflicts": [],
    "variants": [
        {
            "name": "build_system",
            "default": "cmake",
            "description": "Build systems supported by the package"
        },
        {
            "name": "build_type",
            "default": "RelWithDebInfo",
            "description": "CMake build type"
        },
        {
            "name": "ipo",
            "default": false,
            "description": "CMake interprocedural optimization"
        },
        {
            "name": "generator",
            "default": "make",
            "description": "the build system generator to use"
        },
        {
            "name": "layouts",
            "default": true,
            "description": "Build Kokkos View/DynRankView with layout variants"
        },
        {
            "name": "memory_traits",
            "default": true,
            "description": "Build Kokkos View/DynRankView with memory trait variants"
        },
        {
            "name": "view_ranks",
            "default": "4",
            "description": "Max Kokkos View dimensions"
        }
    ],
    "homepage": "https://github.com/kokkos/pykokkos-base.git",
    "maintainers": [
        "adamjstewart",
        "jrmadsen",
        "pradyunsg"
    ],
    "patches": [],
    "resources": [],
    "description": "Minimal set of bindings for Kokkos interoperability with Python\n(initialize, finalize, View, DynRankView, Kokkos-tools)\n",
    "dependencies": [
        {
            "name": "cmake",
            "description": "A cross-platform, open-source build system. CMake is a family of tools\ndesigned to build, test and package software."
        },
        {
            "name": "gmake",
            "description": "GNU Make is a tool which controls the generation of executables and\nother non-source files of a program from the program's source files."
        },
        {
            "name": "ninja",
            "description": "Ninja is a small build system with a focus on speed. It differs from\nother build systems in two major respects: it is designed to have its\ninput files generated by a higher-level build system, and it is designed\nto run builds as fast as possible."
        },
        {
            "name": "python",
            "description": "The Python programming language."
        },
        {
            "name": "py-pybind11",
            "description": "pybind11 -- Seamless operability between C++11 and Python. pybind11 is a\nlightweight header-only library that exposes C++ types in Python and\nvice versa, mainly to create Python bindings of existing C++ code. Its\ngoals and syntax are similar to the excellent Boost.Python library by\nDavid Abrahams: to minimize boilerplate code in traditional extension\nmodules by inferring type information using compile-time introspection."
        },
        {
            "name": "kokkos",
            "description": "Kokkos implements a programming model in C++ for writing performance\nportable applications targeting all major HPC platforms."
        }
    ],
    "dependent_to": []
}