{
    "name": "py-poetry",
    "aliases": [],
    "versions": [
        {
            "name": "1.2.1",
            "sha256": "2750bb2b636ef435d8beac51dde0b13d06199017a1d9b96cba899863d1e81024"
        },
        {
            "name": "1.2.0",
            "sha256": "17c527d5d5505a5a7c5c14348d87f077d643cf1f186321530cde68e530bba59f"
        },
        {
            "name": "1.1.13",
            "sha256": "b905ed610085f568aa61574e0e09260c02bff9eae12ff672af39e9f399357ac4"
        },
        {
            "name": "1.1.12",
            "sha256": "5c66e2357fe37b552462a88b7d31bfa2ed8e84172208becd666933c776252567"
        }
    ],
    "latest_version": "1.2.1",
    "build_system": "PythonPackage",
    "conflicts": [],
    "variants": [
        {
            "name": "build_system",
            "default": "python_pip",
            "description": "Build systems supported by the package"
        }
    ],
    "homepage": "https://python-poetry.org/",
    "maintainers": [
        "adamjstewart",
        "pradyunsg"
    ],
    "patches": [],
    "resources": [],
    "description": "Python dependency management and packaging made easy.\n",
    "dependencies": [
        {
            "name": "python",
            "description": "The Python programming language."
        },
        {
            "name": "py-pip",
            "description": "The PyPA recommended tool for installing Python packages."
        },
        {
            "name": "py-wheel",
            "description": "A built-package format for Python."
        },
        {
            "name": "py-poetry-core",
            "description": "Poetry PEP 517 Build Backend."
        },
        {
            "name": "py-poetry-plugin-export",
            "description": "Poetry plugin to export the dependencies to various formats"
        },
        {
            "name": "py-backports-cached-property",
            "description": "cached_property() - computed once per instance, cached as attribute"
        },
        {
            "name": "py-cachecontrol",
            "description": "CacheControl is a port of the caching algorithms in httplib2 for use\nwith requests session object."
        },
        {
            "name": "py-cachy",
            "description": "Cachy provides a simple yet effective caching library."
        },
        {
            "name": "py-cleo",
            "description": "Cleo allows you to create beautiful and testable command-line\ninterfaces."
        },
        {
            "name": "py-clikit",
            "description": "CliKit is a group of utilities to build beautiful and testable command\nline interfaces."
        },
        {
            "name": "py-crashtest",
            "description": "Crashtest is a Python library that makes exceptions handling and\ninspection easier."
        },
        {
            "name": "py-html5lib",
            "description": "HTML parser based on the WHATWG HTML specification."
        },
        {
            "name": "py-importlib-metadata",
            "description": "Read metadata from Python packages."
        },
        {
            "name": "py-jsonschema",
            "description": "Jsonschema: An(other) implementation of JSON Schema for Python."
        },
        {
            "name": "py-keyring",
            "description": "The Python keyring library provides an easy way to access the system\nkeyring service from python. It can be used in any application that\nneeds safe password storage."
        },
        {
            "name": "py-packaging",
            "description": "Core utilities for Python packages."
        },
        {
            "name": "py-pexpect",
            "description": "Pexpect allows easy control of interactive console applications."
        },
        {
            "name": "py-pkginfo",
            "description": "Query metadatdata from sdists / bdists / installed packages."
        },
        {
            "name": "py-platformdirs",
            "description": "A small Python module for determining appropriate platform-specific\ndirs, e.g. a \"user data dir\""
        },
        {
            "name": "py-requests",
            "description": "Python HTTP for Humans."
        },
        {
            "name": "py-requests-toolbelt",
            "description": "A toolbelt of useful classes and functions to be used with python-\nrequests"
        },
        {
            "name": "py-shellingham",
            "description": "Tool to Detect Surrounding Shell"
        },
        {
            "name": "py-tomlkit",
            "description": "Style preserving TOML library"
        },
        {
            "name": "py-virtualenv",
            "description": "virtualenv is a tool to create isolated Python environments."
        },
        {
            "name": "py-xattr",
            "description": "A python interface to access extended file attributes, sans libattr\ndependency."
        },
        {
            "name": "py-urllib3",
            "description": "HTTP library with thread-safe connection pooling, file post, and more."
        },
        {
            "name": "py-dulwich",
            "description": "Dulwich aims to provide an interface to Git repos (both local and\nremote) that doesn't call out to Git directory, but instead uses pure\nPython."
        }
    ],
    "dependent_to": [
        {
            "name": "py-graphlib-backport",
            "description": "Backport of the Python 3.9 graphlib module for Python 3.6+."
        },
        {
            "name": "py-questionary",
            "description": "Questionary is a Python library for effortlessly building pretty command\nline interfaces."
        },
        {
            "name": "py-stomp-py",
            "description": "Python client library for accessing messaging servers (such as ActiveMQ,\nArtemis or RabbitMQ) using the STOMP protocol (STOMP v1.0, STOMP v1.1\nand STOMP v1.2)"
        },
        {
            "name": "py-flatten-dict",
            "description": "A flexible utility for flattening and unflattening dict-lik objects in\nPython"
        },
        {
            "name": "py-maestrowf",
            "description": "A general purpose workflow conductor for running multi-step simulation\nstudies."
        },
        {
            "name": "py-pkgconfig",
            "description": "Interface Python with pkg-config."
        },
        {
            "name": "py-fastapi-utils",
            "description": "Reusable utilities for FastAPI"
        },
        {
            "name": "py-url-normalize",
            "description": "URL normalization for Python."
        }
    ]
}