{
    "name": "py-qiskit-terra",
    "aliases": [],
    "versions": [
        {
            "name": "0.18.3",
            "sha256": "8737c8f1f4c6f29ec2fb02d73023f4854a396c33f78f4629a861a3e48fc789cc"
        }
    ],
    "latest_version": "0.18.3",
    "build_system": "PythonPackage",
    "conflicts": [],
    "variants": [],
    "homepage": "https://github.com/Qiskit/qiskit-terra",
    "maintainers": [
        "adamjstewart"
    ],
    "patches": [],
    "resources": [],
    "description": "Qiskit is an open-source SDK for working with quantum computers at the\nlevel of extended quantum circuits, operators, and algorithms.\n",
    "dependencies": [
        {
            "name": "python",
            "description": "The Python programming language."
        },
        {
            "name": "py-pip",
            "description": "The PyPA recommended tool for installing Python packages."
        },
        {
            "name": "py-wheel",
            "description": "A built-package format for Python."
        },
        {
            "name": "py-setuptools",
            "description": "A Python utility that aids in the process of downloading, building,\nupgrading, installing, and uninstalling Python packages."
        },
        {
            "name": "py-cython",
            "description": "The Cython compiler for writing C extensions for the Python language."
        },
        {
            "name": "py-contextvars",
            "description": "This package implements a backport of Python 3.7 contextvars module (see\nPEP 567) for Python 3.6."
        },
        {
            "name": "py-jsonschema",
            "description": "Jsonschema: An(other) implementation of JSON Schema for Python."
        },
        {
            "name": "py-retworkx",
            "description": "A high performance Python graph library implemented in Rust."
        },
        {
            "name": "py-numpy",
            "description": "NumPy is the fundamental package for scientific computing with Python.\nIt contains among other things: a powerful N-dimensional array object,\nsophisticated (broadcasting) functions, tools for integrating C/C++ and\nFortran code, and useful linear algebra, Fourier transform, and random\nnumber capabilities"
        },
        {
            "name": "py-scipy",
            "description": "SciPy (pronounced \"Sigh Pie\") is a Scientific Library for Python. It\nprovides many user-friendly and efficient numerical routines such as\nroutines for numerical integration and optimization."
        },
        {
            "name": "py-ply",
            "description": "Python Lex & Yacc."
        },
        {
            "name": "py-psutil",
            "description": "psutil is a cross-platform library for retrieving information on running\nprocesses and system utilization (CPU, memory, disks, network) in\nPython."
        },
        {
            "name": "py-sympy",
            "description": "SymPy is a Python library for symbolic mathematics."
        },
        {
            "name": "py-dill",
            "description": "Serialize all of python"
        },
        {
            "name": "py-fastjsonschema",
            "description": "Fast JSON schema validator for Python."
        },
        {
            "name": "py-python-constraint",
            "description": "Constraint Solving Problem resolver for Python"
        },
        {
            "name": "py-python-dateutil",
            "description": "Extensions to the standard Python datetime module."
        },
        {
            "name": "py-symengine",
            "description": "Python wrappers for SymEngine, a symbolic manipulation library."
        },
        {
            "name": "py-tweedledum",
            "description": "tweedledum is a library for synthesis, compilation, and optimization of\nquantum circuits. The library is written to be scalable up to problem\nsizes in which quantum circuits outperform classical ones. Also, it is\nmeant to be used both independently and alongside established tools."
        }
    ],
    "dependent_to": [
        {
            "name": "py-qiskit-aer",
            "description": "Aer is a high performance simulator for quantum circuits that includes\nnoise models"
        }
    ]
}