{
    "name": "r-car",
    "aliases": [],
    "versions": [
        {
            "name": "3.1-2",
            "sha256": "89263491977ac8e9406b2f4b1638bf06c7ddd1b0e0e3ecda4be61420474674c8"
        },
        {
            "name": "3.1-1",
            "sha256": "8fc55815eed7e46a32b54da9e0bfa4b74a8d082d73d896e3372f2a413b6bd2bc"
        },
        {
            "name": "3.1-0",
            "sha256": "bd52b4eaea46ce828fccd93445301d06ebd265e2ffff796064875a8c0f0aea21"
        },
        {
            "name": "3.0-13",
            "sha256": "d35ae8da80284c9e4471ff13e7100c3cdc1809fd06f813cd223a3958e29e47eb"
        },
        {
            "name": "3.0-12",
            "sha256": "b899a6efae3842a90a2349d381dbcf4b4ed36bd03108ebe7380e81120e457302"
        },
        {
            "name": "3.0-11",
            "sha256": "b32c927206f515631ff276dbb337b0f22e9b2d851f4abb1d2c272e534c19542c"
        },
        {
            "name": "3.0-10",
            "sha256": "1ce316d2fee9b47c951d25d096be732489a3c9f6fc9e612a1eca2e50fb5925f1"
        },
        {
            "name": "3.0-3",
            "sha256": "fa807cb12f6e7fb38ec534cac4eef54747945c2119a7d51155a2492ad778c36f"
        },
        {
            "name": "3.0-2",
            "sha256": "df59a9ba8fed67eef5ddb8f92f2b41745df715d5695c71d562d7031513f37c50"
        },
        {
            "name": "2.1-4",
            "sha256": "fd39cf1750cb560a66623fea3fa9e6a94fc24e3dc36367aff24df7d0743edb28"
        },
        {
            "name": "2.1-2",
            "sha256": "8cc3e57f172c8782a08960b508906d3201596a21f4b6c1dab8d4e59353093652"
        }
    ],
    "latest_version": "3.1-2",
    "build_system": "RPackage",
    "conflicts": [],
    "variants": [
        {
            "name": "build_system",
            "default": "generic",
            "description": "Build systems supported by the package"
        }
    ],
    "homepage": "https://cloud.r-project.org/package=car",
    "maintainers": [],
    "patches": [],
    "resources": [],
    "description": "Companion to Applied Regression. Functions and Datasets to Accompany J.\nFox and S. Weisberg, An R Companion to Applied Regression, Second\nEdition, Sage, 2011.\n",
    "dependencies": [
        {
            "name": "r",
            "description": "R is 'GNU S', a freely available language and environment for\nstatistical computing and graphics which provides a wide variety of\nstatistical and graphical techniques: linear and nonlinear modelling,\nstatistical tests, time series analysis, classification, clustering,\netc. Please consult the R project homepage for further information."
        },
        {
            "name": "r-abind",
            "description": "Combine Multidimensional Arrays. Combine multidimensional arrays into a\nsingle array. This is a generalization of 'cbind' and 'rbind'. Works\nwith vectors, matrices, and higher-dimensional arrays. Also provides\nfunctions 'adrop', 'asub', and 'afill' for manipulating, extracting and\nreplacing data in arrays."
        },
        {
            "name": "r-cardata",
            "description": "Companion to Applied Regression Data Sets. Datasets to Accompany J. Fox\nand S. Weisberg, An R Companion to Applied Regression, Third Edition,\nSage (2019)."
        },
        {
            "name": "r-lme4",
            "description": "Linear Mixed-Effects Models using 'Eigen' and S4. Fit linear and\ngeneralized linear mixed-effects models. The models and their components\nare represented using S4 classes and methods. The core computational\nalgorithms are implemented using the 'Eigen' C++ library for numerical\nlinear algebra and 'RcppEigen' \"glue\"."
        },
        {
            "name": "r-maptools",
            "description": "Tools for Handling Spatial Objects. Set of tools for manipulating and\nreading geographic data, in particular ESRI shapefiles; C code used from\nshapelib. It includes binary access to GSHHG shoreline files. The\npackage also provides interface wrappers for exchanging spatial objects\nwith packages such as PBSmapping, spatstat, maps, RArcInfo, Stata tmap,\nWinBUGS, Mondrian, and others."
        },
        {
            "name": "r-mass",
            "description": "Support Functions and Datasets for Venables and Ripley's MASS. Functions\nand datasets to support Venables and Ripley, \"Modern Applied Statistics\nwith S\" (4th edition, 2002)."
        },
        {
            "name": "r-mgcv",
            "description": "Mixed GAM Computation Vehicle with Automatic Smoothness Estimation.\nGeneralized additive (mixed) models, some of their extensions and other\ngeneralized ridge regression with multiple smoothing parameter\nestimation by (Restricted) Marginal Likelihood, Generalized Cross\nValidation and similar, or using iterated nested Laplace approximation\nfor fully Bayesian inference. See Wood (2017)\n<doi:10.1201/9781315370279> for an overview. Includes a gam() function,\na wide variety of smoothers, 'JAGS' support and distributions beyond the\nexponential family."
        },
        {
            "name": "r-nlme",
            "description": "Linear and Nonlinear Mixed Effects Models. Fit and compare Gaussian\nlinear and nonlinear mixed-effects models."
        },
        {
            "name": "r-nnet",
            "description": "Feed-Forward Neural Networks and Multinomial Log-Linear Models. Software\nfor feed-forward neural networks with a single hidden layer, and for\nmultinomial log-linear models."
        },
        {
            "name": "r-pbkrtest",
            "description": "Parametric Bootstrap, Kenward-Roger and Satterthwaite Based Methods for\nTest in Mixed Models. Test in mixed effects models. Attention is on\nmixed effects models as implemented in the 'lme4' package. For linear\nmixed models, this package implements (1) a parametric bootstrap test,\n(2) a Kenward-Roger-typ modification of F-tests for linear mixed effects\nmodels and (3) a Satterthwaite-type modification of F-tests for linear\nmixed effects models. The package also implements a parametric bootstrap\ntest for generalized linear mixed models. The facilities of the package\nare documented in the paper by Halehoh and Hojsgaard, (2012,\n<doi:10.18637/jss.v059.i09>). Please see 'citation(\"pbkrtest\")' for\ncitation details."
        },
        {
            "name": "r-quantreg",
            "description": "Quantile Regression. Estimation and inference methods for models of\nconditional quantiles: Linear and nonlinear parametric and non-\nparametric (total variation penalized) models for conditional quantiles\nof a univariate response and several methods for handling censored\nsurvival data. Portfolio selection methods based on expected shortfall\nrisk are also now included. See Koenker (2006)\n<doi:10.1017/CBO9780511754098> and Koenker et al. (2017)\n<doi:10.1201/9781315120256>."
        },
        {
            "name": "r-rio",
            "description": "A Swiss-Army Knife for Data I/O. Streamlined data import and export by\nmaking assumptions that the user is probably willing to make: 'import()'\nand 'export()' determine the data structure from the file extension,\nreasonable defaults are used for data import and export (e.g.,\n'stringsAsFactors=FALSE'), web-based import is natively supported\n(including from SSL/HTTPS), compressed files can be read directly\nwithout explicit decompression, and fast import packages are used where\nappropriate. An additional convenience function, 'convert()', provides a\nsimple method for converting between file types."
        },
        {
            "name": "r-scales",
            "description": "Scale Functions for Visualization. Graphical scales map data to\naesthetics, and provide methods for automatically determining breaks and\nlabels for axes and legends."
        }
    ],
    "dependent_to": [
        {
            "name": "r-twosamplemr",
            "description": "Two Sample MR functions and interface to MR Base database. A package for\nperforming Mendelian randomization using GWAS summary data. It uses the\nIEU GWAS database to obtain data automatically, and a wide range of\nmethods to run the analysis. You can use the MR-Base web app to try out\na limited range of the functionality in this package, but for any\nserious work we strongly recommend using this R package."
        },
        {
            "name": "r-rstatix",
            "description": "Pipe-Friendly Framework for Basic Statistical Tests. Provides a simple\nand intuitive pipe-friendly framework, coherent with the 'tidyverse'\ndesign philosophy, for performing basic statistical tests, including\nt-test, Wilcoxon test, ANOVA, Kruskal-Wallis and correlation analyses.\nThe output of each test is automatically transformed into a tidy data\nframe to facilitate visualization. Additional functions are available\nfor reshaping, reordering, manipulating and visualizing correlation\nmatrix. Functions are also included to facilitate the analysis of\nfactorial experiments, including purely 'within-Ss' designs (repeated\nmeasures), purely 'between-Ss' designs, and mixed 'within-and-between-\nSs' designs. It's also possible to compute several effect size metrics,\nincluding \"eta squared\" for ANOVA, \"Cohen's d\" for t-test and 'Cramer V'\nfor the association between categorical variables. The package contains\nhelper functions for identifying univariate and multivariate outliers,\nassessing normality and homogeneity of variances."
        },
        {
            "name": "r-afex",
            "description": "Analysis of Factorial Experiments. Convenience functions for analyzing\nfactorial experiments using ANOVA or mixed models. aov_ez(), aov_car(),\nand aov_4() allow specification of between, within (i.e., repeated-\nmeasures), or mixed (i.e., split-plot) ANOVAs for data in long format\n(i.e., one observation per row), automatically aggregating multiple\nobservations per individual and cell of the design. mixed() fits mixed\nmodels using lme4::lmer() and computes p-values for all fixed effects\nusing either Kenward-Roger or Satterthwaite approximation for degrees of\nfreedom (LMM only), parametric bootstrap (LMMs and GLMMs), or likelihood\nratio tests (LMMs and GLMMs). afex_plot() provides a high-level\ninterface for interaction or one-way plots using ggplot2, combining raw\ndata and model estimates. afex uses type 3 sums of squares as default\n(imitating commercial statistical software)."
        },
        {
            "name": "r-caret",
            "description": "Classification and Regression Training. Misc functions for training and\nplotting classification and regression models."
        },
        {
            "name": "r-factominer",
            "description": "Multivariate Exploratory Data Analysis and Data Mining. Exploratory data\nanalysis methods to summarize, visualize and describe datasets. The main\nprincipal component methods are available, those with the largest\npotential in terms of applications: principal component analysis (PCA)\nwhen variables are quantitative, correspondence analysis (CA) and\nmultiple correspondence analysis (MCA) when variables are categorical,\nMultiple Factor Analysis when variables are structured in groups, etc.\nand hierarchical cluster analysis. F. Husson, S. Le and J. Pages (2017)."
        },
        {
            "name": "r-aer",
            "description": "Applied Econometrics with R. Functions, data sets, examples, demos, and\nvignettes for the book Christian Kleiber and Achim Zeileis (2008),\nApplied Econometrics with R, Springer-Verlag, New York. ISBN\n978-0-387-77316-2."
        }
    ]
}