{
    "name": "r-rhdf5filters",
    "aliases": [],
    "versions": [
        {
            "name": "1.10.0",
            "commit": "6131538e2c5896dca0af33882bc2da961d79e49a"
        },
        {
            "name": "1.8.0",
            "commit": "b0b588b71a5595b30f4e698a50b84310dc19745d"
        },
        {
            "name": "1.6.0",
            "commit": "5f7f3a5b7dabd6e7d0c50cda70290e2472ff4f53"
        },
        {
            "name": "1.2.0",
            "commit": "25af0180f926b4b3ea11b30ec9277d26ad3d56b3"
        }
    ],
    "latest_version": "1.10.0",
    "build_system": "RPackage",
    "conflicts": [],
    "variants": [
        {
            "name": "build_system",
            "default": "generic",
            "description": "Build systems supported by the package"
        }
    ],
    "homepage": "https://bioconductor.org/packages/rhdf5filters",
    "maintainers": [
        "glennpj"
    ],
    "patches": [],
    "resources": [],
    "description": "HDF5 Compression Filters. Provides a collection of compression filters\nfor use with HDF5 datasets.\n",
    "dependencies": [
        {
            "name": "r",
            "description": "R is 'GNU S', a freely available language and environment for\nstatistical computing and graphics which provides a wide variety of\nstatistical and graphical techniques: linear and nonlinear modelling,\nstatistical tests, time series analysis, classification, clustering,\netc. Please consult the R project homepage for further information."
        },
        {
            "name": "r-rhdf5lib",
            "description": "hdf5 library as an R package. Provides C and C++ hdf5 libraries."
        },
        {
            "name": "gmake",
            "description": "GNU Make is a tool which controls the generation of executables and\nother non-source files of a program from the program's source files."
        }
    ],
    "dependent_to": [
        {
            "name": "r-hdf5array",
            "description": "HDF5 backend for DelayedArray objects. Implements the HDF5Array and\nTENxMatrix classes, 2 convenient and memory-efficient array-like\ncontainers for on-disk representation of HDF5 datasets. HDF5Array is for\ndatasets that use the conventional (i.e. dense) HDF5 representation.\nTENxMatrix is for datasets that use the HDF5-based sparse matrix\nrepresentation from 10x Genomics (e.g. the 1.3 Million Brain Cell\nDataset). Both containers being DelayedArray extensions, they support\nall operations supported by DelayedArray objects. These operations can\nbe either delayed or block-processed."
        },
        {
            "name": "r-rhdf5",
            "description": "R Interface to HDF5. This package provides an interface between HDF5 and\nR. HDF5's main features are the ability to store and access very large\nand/or complex datasets and a wide variety of metadata on mass storage\n(disk) through a completely portable file format. The rhdf5 package is\nthus suited for the exchange of large and/or complex datasets between R\nand other software package, and for letting R applications work on\ndatasets that are larger than the available RAM."
        }
    ]
}