{
    "aliases": [],
    "build_system": "MakefilePackage",
    "conflicts": [
        {
            "description": null,
            "name": "arch=windows-None-None",
            "spec": "build_system=makefile"
        }
    ],
    "dependencies": [
        {
            "description": "GNU Make is a tool which controls the generation of executables and\nother non-source files of a program from the program's source files.",
            "name": "gmake"
        }
    ],
    "dependent_to": [
        {
            "description": "SST Elements implements a range of components for performing\narchitecture simulation from node-level to system-level using the SST\ndiscrete event core.",
            "name": "sst-elements"
        }
    ],
    "description": " Ramulator is a fast and cycle-accurate DRAM simulator that supports a\nwide array of commercial, as well as academic, DRAM standards.\n",
    "homepage": "https://github.com/CMU-SAFARI/ramulator",
    "latest_version": "sst",
    "maintainers": [
        "jjwilke"
    ],
    "name": "ramulator",
    "patches": [
        {
            "level": 1,
            "owner": "builtin.ramulator",
            "relative_path": "ramulator_sha_7d2e723_gcc48Patch.patch",
            "reverse": false,
            "sha256": "6698ec6507cb5565a8cad626e1412f280ab0303a72b4f75bdcf7f19c0704ee30",
            "version": "@sst",
            "working_dir": "."
        },
        {
            "level": 1,
            "owner": "builtin.ramulator",
            "relative_path": "ramulator_sha_7d2e723_libPatch.patch",
            "reverse": false,
            "sha256": "a1ed80d5430a36bdbc75b75bfae8ada9d4fd086f8d1bb77d450cef38dcf46c64",
            "version": "@sst",
            "working_dir": "."
        }
    ],
    "resources": [],
    "variants": [
        {
            "default": "makefile",
            "description": "Build systems supported by the package",
            "name": "build_system"
        }
    ],
    "versions": [
        {
            "commit": "7d2e72306c6079768e11a1867eb67b60cee34a1c",
            "name": "sst"
        }
    ],
    "versions_deprecated": []
}