{
    "name": "unibilium",
    "aliases": [],
    "versions": [
        {
            "name": "2.0.0",
            "sha256": "78997d38d4c8177c60d3d0c1aa8c53fd0806eb21825b7b335b1768d7116bc1c1"
        },
        {
            "name": "1.2.0",
            "sha256": "623af1099515e673abfd3cae5f2fa808a09ca55dda1c65a7b5c9424eb304ead8"
        }
    ],
    "latest_version": "2.0.0",
    "build_system": "Package",
    "conflicts": [],
    "variants": [
        {
            "name": "build_system",
            "default": "generic",
            "description": "Build systems supported by the package"
        }
    ],
    "homepage": "https://github.com/mauke/unibilium",
    "maintainers": [],
    "patches": [],
    "resources": [],
    "description": "A terminfo parsing library\n",
    "dependencies": [
        {
            "name": "libtool",
            "description": "libtool -- library building part of autotools."
        },
        {
            "name": "perl",
            "description": "Perl 5 is a highly capable, feature-rich programming language with over\n27 years of development."
        },
        {
            "name": "gzip",
            "description": "GNU Gzip is a popular data compression program originally written by\nJean-loup Gailly for the GNU project."
        }
    ],
    "dependent_to": [
        {
            "name": "neovim",
            "description": "Neovim: Vim-fork focused on extensibility and usability"
        },
        {
            "name": "libtermkey",
            "description": "Easy keyboard entry processing for terminal programs"
        }
    ]
}